MANIFEST.in
README.md
setup.py
penny/__init__.py
penny/geo_lookup.py
penny/headers.py
penny/inspectors.py
penny/list_checks.py
penny/value_checks.py
penny.egg-info/PKG-INFO
penny.egg-info/SOURCES.txt
penny.egg-info/dependency_links.txt
penny.egg-info/not-zip-safe
penny.egg-info/requires.txt
penny.egg-info/top_level.txt
penny/data/GeoLite2-City-Locations.csv
penny/data/ISO3166ErrorDictionary.csv