Metadata-Version: 1.1
Name: penny
Version: 0.4.1
Summary: Inspect your data. Find the truth!
Home-page: https://github.com/gati/penny
Author: Jonathon Morgan
Author-email: jonathon@goodattheinternet.com
License: MIT
Download-URL: https://github.com/gati/penny/tarball/0.4.1
Platform: UNKNOWN
